{
    "name": "Space Theme",
    "src": "\n        div.modal-content {\n            background-color: #290e4380 !important;\n        }\n        span.modal__title {\n            color: #fbffe0 !important;\n        }\n        div.modal__content {\n            color: #fbffe0 !important;\n        }\n        span.drc-modal-title {\n            color: #fbffe0 !important;\n        }\n        div.drc-modal-modal-content {\n            background-color: #290e4380 !important;\n        }\n        body .el-input__wrapper, body .el-textarea__wrapper {\n            background-color: #290e4380 !important;\n        }\n        .animals-container .animals .animal {\n            --tw-bg-opacity: 0.5 !important\n        }\n        .dark .forum-page {\n            --tw-bg-opacity: 0.5 !important\n        }\n        .dark .forum-page .inner .forum-posts .post-summary .forum-post-summary {\n            background-color: #290e4380 !important\n        }\n        .dark .forum-page .inner .forum-posts .post-summary .forum-post-summary:hover {\n            background-color: #290e4380 !important\n        }\n        .dark .forum-post-page .inner {\n            background-color: #290e4380 !important\n        }  \n        div.loading-bar > div {\n            background-color: #fff700 !important;\n        }\n        \n            .home-page .home-bg {\n                background-image: url(https://deeeep-reef-client.github.io/plugins-api/plugins/space-theme/bgimage.jpg) !important;\n            }\n            \n        \n            .loading-container {\n                background-image: url(https://deeeep-reef-client.github.io/plugins-api/plugins/space-theme/loadingbg.jpg) !important;\n            }\n            \n        \n                        div.loading-bar > img.ball {\n                            display: block !important;\n                            box-sizing: border-box !important;\n                            background: url(https://deeeep-reef-client.github.io/plugins-api/plugins/space-theme/loadingball.png) no-repeat !important;\n                            width: 128px !important;\n                            height: 64px !important;\n                            padding-left: 128px !important;\n                        }\n                        \n        ",
    "themedata": {
        "bgImage": "https://deeeep-reef-client.github.io/plugins-api/plugins/space-theme/bgimage.jpg",
        "loadingBgImage": "https://deeeep-reef-client.github.io/plugins-api/plugins/space-theme/loadingbg.jpg",
        "modalBgColour": "#290e43",
        "modalTextColour": "#fbffe0",
        "modalTransparency": "5",
        "loadingIconImage": "https://deeeep-reef-client.github.io/plugins-api/plugins/space-theme/loadingball.png",
        "loadingBarColour": "#fff700"
    }
}